commlib/.editorconfig
commlib/__init__.py
commlib/action.py
commlib/async_utils.py
commlib/bridges.py
commlib/compression.py
commlib/connection.py
commlib/endpoints.py
commlib/exceptions.py
commlib/msg.py
commlib/node.py
commlib/pubsub.py
commlib/rpc.py
commlib/serializer.py
commlib/tcp_proxy.py
commlib/timer.py
commlib/transports/__init__.py
commlib/transports/amqp.py
commlib/transports/base_transport.py
commlib/transports/kafka.py
commlib/transports/mock.py
commlib/transports/mqtt.py
commlib/transports/redis.py
commlib/utils.py
commlib_py-0.11.4.dist-info/LICENSE
commlib_py-0.11.4.dist-info/LICENSE.txt
commlib_py-0.11.4.dist-info/METADATA
commlib_py-0.11.4.dist-info/WHEEL
commlib_py-0.11.4.dist-info/RECORD
