Metadata-Version: 2.1
Name: commlib-py
Version: 0.11.4
Summary: Internal DSL for communication and messaging in CyberPhysical Systems
Author: Konstantinos Panayiotou
Author-email: klpanagi@gmail.com
Requires-Python: >=3.7,<4.0
Classifier: Programming Language :: Python :: 3
Classifier: Programming Language :: Python :: 3.7
Classifier: Programming Language :: Python :: 3.8
Classifier: Programming Language :: Python :: 3.9
Classifier: Programming Language :: Python :: 3.10
Classifier: Programming Language :: Python :: 3.11
Classifier: Programming Language :: Python :: 3.12
Requires-Dist: paho-mqtt (>=1.6.1,<2.0.0)
Requires-Dist: pika (>=1.3.1,<2.0.0)
Requires-Dist: pydantic (>=2.0.0,<3.0.0)
Requires-Dist: redis[hiredis] (>=5.0.1,<6.0.0)
Requires-Dist: requests (>=2.1.0,<3.0.0)
Requires-Dist: rich (>=13.7.0,<14.0.0)
Requires-Dist: ujson (>=5.7.0,<6.0.0)
Requires-Dist: wheel (>=0.38.0)
